detectors/__init__.py
detectors/config.py
detectors/criterions.py
detectors/ensemble.py
detectors/eval.py
detectors/scod_eval.py
detectors/trainer.py
detectors/utils.py
detectors/aggregations/__init__.py
detectors/aggregations/anomaly.py
detectors/aggregations/basics.py
detectors/aggregations/cosine.py
detectors/aggregations/innerprod.py
detectors/aggregations/mahalanobis.py
detectors/aggregations/power.py
detectors/aggregations/quantile.py
detectors/aggregations/supervised.py
detectors/data/__init__.py
detectors/data/cifar_wrapper.py
detectors/data/cifarc.py
detectors/data/cifarlt.py
detectors/data/constants.py
detectors/data/english_chars.py
detectors/data/imagenet.py
detectors/data/imagenetlt.py
detectors/data/isun.py
detectors/data/lsun_r_c.py
detectors/data/mnist_wrapped.py
detectors/data/mnistc.py
detectors/data/mos.py
detectors/data/ninco_ssb_clean.py
detectors/data/noise.py
detectors/data/openimage_o.py
detectors/data/places365.py
detectors/data/textures.py
detectors/data/tiny_imagenet.py
detectors/data/tiny_imagenet_r_c.py
detectors/data/utils.py
detectors/data/wilds_ds.py
detectors/data/OpenImageO/openimage_o_urls.csv
detectors/methods/__init__.py
detectors/methods/ae.py
detectors/methods/argmax.py
detectors/methods/bats.py
detectors/methods/csi.py
detectors/methods/dice.py
detectors/methods/doctor.py
detectors/methods/energy.py
detectors/methods/entropy.py
detectors/methods/gmm.py
detectors/methods/gmm_torch.py
detectors/methods/godin.py
detectors/methods/gradnorm.py
detectors/methods/gram.py
detectors/methods/igeood_logits.py
detectors/methods/kl_matching.py
detectors/methods/knn_cosine.py
detectors/methods/knn_euclides.py
detectors/methods/knn_projection.py
detectors/methods/l1norm.py
detectors/methods/logit_norm.py
detectors/methods/mahalanobis.py
detectors/methods/max_logits.py
detectors/methods/maxcosine.py
detectors/methods/mcdropout.py
detectors/methods/msp.py
detectors/methods/naive.py
detectors/methods/odin.py
detectors/methods/oe.py
detectors-0.1.11.dist-info/LICENSE
detectors-0.1.11.dist-info/METADATA
detectors-0.1.11.dist-info/WHEEL
detectors-0.1.11.dist-info/top_level.txt
detectors-0.1.11.dist-info/RECORD
