Metadata-Version: 2.1
Name: detectors
Version: 0.1.11
Summary: Detectors: a python package to benchmark generalized out-of-distribution detection methods.
Home-page: https://github.com/edadaltocg/detectors
Author: Eduardo Dadalto
Author-email: edadaltocg@gmail.com
License: APACHE 2.0
Keywords: vision deep learning pytorch OOD
Classifier: Intended Audience :: Developers
Classifier: Intended Audience :: Education
Classifier: Intended Audience :: Science/Research
Classifier: Operating System :: OS Independent
Classifier: License :: OSI Approved :: MIT License
Classifier: Programming Language :: Python :: 3
Classifier: Programming Language :: Python :: 3.8
Classifier: Programming Language :: Python :: 3.9
Classifier: Programming Language :: Python :: 3.10
Classifier: Topic :: Scientific/Engineering :: Artificial Intelligence
Requires-Python: >=3.8.0
License-File: LICENSE
Requires-Dist: Pillow
Requires-Dist: numpy
Requires-Dist: optuna
Requires-Dist: scikit-learn
Requires-Dist: scikit-image
Requires-Dist: timm >=0.8.19.dev0
Requires-Dist: torch >=1.13.1
Requires-Dist: torchvision
Requires-Dist: tqdm
Requires-Dist: scipy
Requires-Dist: accelerate
Requires-Dist: psutil
Requires-Dist: pandas
Requires-Dist: wilds
Requires-Dist: faiss-cpu
Requires-Dist: matplotlib
Provides-Extra: dev
Requires-Dist: black ; extra == 'dev'
Requires-Dist: isort ; extra == 'dev'
Requires-Dist: flake8 ; extra == 'dev'
Requires-Dist: pytest ; extra == 'dev'
Requires-Dist: pytest-cov ; extra == 'dev'
Requires-Dist: pytest-timeout ; extra == 'dev'
Requires-Dist: pytest-xdist ; extra == 'dev'
Requires-Dist: twine ; extra == 'dev'
Requires-Dist: sphinx ; extra == 'dev'
Requires-Dist: sphinx-rtd-theme ; extra == 'dev'
Requires-Dist: myst-parser ; extra == 'dev'
Requires-Dist: six ; extra == 'dev'
